{"asset": "AUD/JPY", "timeframe": "1PM-3PM", "strike": "75.87", "direction": "+", "timestamp": "1563216466.0121741"}
{"asset": "AUD/JPY", "timeframe": "1PM-3PM", "strike": "75.87", "direction": "+", "timestamp": "1563216574.4269493"}
{"asset": "AUD/JPY", "timeframe": "1PM-3PM", "strike": "75.87", "direction": "+", "timestamp": "1563216597.5538592"}
{"asset": "AUD/JPY", "timeframe": "1PM-3PM", "strike": "75.87", "direction": "+", "timestamp": "1563216721.650194"}
{"asset": "AUD/JPY", "timeframe": "1PM-3PM", "strike": "75.87", "direction": "+", "timestamp": "1563216750.0276208"}
{"asset": "AUD/JPY", "timeframe": "1PM-3PM", "strike": "75.87", "direction": "+", "timestamp": "1563216791.207154"}
{"asset": "AUD/JPY", "timeframe": "DAILY-3PM", "strike": "75.60", "direction": "+", "timestamp": "1563218388.8276682"}
{"asset": "AUD/JPY", "timeframe": "DAILY-3PM", "strike": "75.60", "direction": "+", "timestamp": "1563218518.277691"}
{"asset": "AUD/JPY", "timeframe": "DAILY-3PM", "strike": "75.60", "direction": "+", "timestamp": "1563218585.3257835"}
{"asset": "AUD/JPY", "timeframe": "DAILY-3PM", "strike": "75.60", "direction": "+", "timestamp": "1563218622.8204165"}
{"asset": "AUD/JPY", "timeframe": "DAILY-3PM", "strike": "75.60", "direction": "+", "timestamp": "1563218773.8256192"}
{"asset": "AUD/JPY", "timeframe": "DAILY-3PM", "strike": "75.60", "direction": "+", "timestamp": "1563218867.1641269"}
{"asset": "AUD/JPY", "timeframe": "DAILY-3PM", "strike": "75.60", "direction": "+", "timestamp": "1563218932.5291917"}
{"asset": "AUD/JPY", "timeframe": "DAILY-3PM", "strike": "75.60", "direction": "+", "timestamp": "1563221560.4066334"}
{"asset": "AUD/JPY", "timeframe": "DAILY-3PM", "strike": "75.60", "direction": "+", "timestamp": "1563221683.4498155"}
{"asset": "AUD/JPY", "timeframe": "DAILY-3PM", "strike": "75.60", "direction": "+", "timestamp": "1563221846.240846"}
{"asset": "AUD/JPY", "timeframe": "DAILY-3PM", "strike": "75.60", "direction": "+", "timestamp": "1563221916.0664916"}
{"asset": "AUD/JPY", "timeframe": "DAILY-3PM", "strike": "75.60", "direction": "+", "timestamp": "1563223466.1648364"}
{"asset": "AUD/JPY", "timeframe": "DAILY-3PM", "strike": "75.60", "direction": "+", "timestamp": "1563223540.3268373"}
{"asset": "AUD/JPY", "timeframe": "DAILY-3PM", "strike": "75.60", "direction": "+", "timestamp": "1563223570.7048173"}
{"asset": "AUD/JPY", "timeframe": "DAILY-3PM", "strike": "75.60", "direction": "+", "timestamp": "1563285623.4207778"}
{"asset": "AUD/JPY", "timeframe": "DAILY-3PM", "strike": "75.60", "direction": "+", "timestamp": "1563285650.186932"}
{"asset": "AUD/JPY", "timeframe": "DAILY-3PM", "strike": "75.60", "direction": "+", "timestamp": "1563285753.4212399"}
{"asset": "AUD/JPY", "timeframe": "DAILY-3PM", "strike": "75.60", "direction": "+", "timestamp": "1563285801.8916726"}
{"asset": "AUD/JPY", "timeframe": "DAILY-3PM", "strike": "75.60", "direction": "+", "timestamp": "1563285842.3723645"}
{"asset": "EUR/USD", "timeframe": "11AM-1PM", "strike": "1.1216", "direction": "+", "timestamp": "1563550879.1241462"}
{"asset": "EUR/USD", "timeframe": "11AM-1PM", "strike": "1.1216", "direction": "+", "timestamp": "1563551055.9802432"}
{"asset": "EUR/USD", "timeframe": "11AM-1PM", "strike": "1.1216", "direction": "+", "timestamp": "1563551926.6684203"}
{"asset": "EUR/USD", "timeframe": "11AM-1PM", "strike": "1.1216", "direction": "+", "timestamp": "1563551933.0225098"}
{"asset": "EUR/USD", "timeframe": "11AM-1PM", "strike": "1.1216", "direction": "+", "timestamp": "1563551975.9316936"}
{"asset": "EUR/USD", "timeframe": "11AM-1PM", "strike": "1.1216", "direction": "+", "timestamp": "1563552192.2157173"}
{"asset": "EUR/USD", "timeframe": "11AM-1PM", "strike": "1.1216", "direction": "+", "timestamp": "1563552249.2485857"}
{"asset": "EUR/USD", "timeframe": "11AM-1PM", "strike": "1.1216", "direction": "+", "timestamp": "1563552315.2866545"}
{"asset": "EUR/USD", "timeframe": "11AM-1PM", "strike": "1.1216", "direction": "+", "timestamp": "1563552511.8128846"}
{"asset": "EUR/USD", "timeframe": "11AM-1PM", "strike": "1.1216", "direction": "+", "timestamp": "1563552552.8986418"}
{"asset": "EUR/USD", "timeframe": "11AM-1PM", "strike": "1.1216", "direction": "+", "timestamp": "1563552639.0039973"}
{"asset": "EUR/USD", "timeframe": "11AM-1PM", "strike": "1.1216", "direction": "+", "timestamp": "1563552704.447086"}
{"asset": "EUR/USD", "timeframe": "11AM-1PM", "strike": "1.1216", "direction": "+", "timestamp": "1563552808.325355"}
{"asset": "EUR/USD", "timeframe": "11AM-1PM", "strike": "1.1216", "direction": "+", "timestamp": "1563552949.245461"}
{"asset": "EUR/USD", "timeframe": "11AM-1PM", "strike": "1.1216", "direction": "+", "timestamp": "1563553081.125701"}
{"asset": "EUR/USD", "timeframe": "11AM-1PM", "strike": "1.1216", "direction": "+", "timestamp": "1563553305.0364904"}
{"asset": "EUR/USD", "timeframe": "11AM-1PM", "strike": "1.1216", "direction": "+", "timestamp": "1563554007.5877104"}
{"asset": "EUR/USD", "timeframe": "11AM-1PM", "strike": "1.1216", "direction": "+", "timestamp": "1563554180.371399"}
{"asset": "EUR/USD", "timeframe": "11AM-1PM", "strike": "1.1216", "direction": "+", "timestamp": "1563554346.3192148"}
{"asset": "EUR/USD", "timeframe": "DAILY-3PM", "strike": "1.1240", "direction": "+", "timestamp": "1563555692.2051537"}
{"asset": "EUR/USD", "timeframe": "DAILY-3PM", "strike": "1.1240", "direction": "+", "timestamp": "1563555804.1650753"}
{"asset": "EUR/USD", "timeframe": "DAILY-3PM", "strike": "1.1240", "direction": "+", "timestamp": "1563555854.0989463"}
{"asset": "EUR/USD", "timeframe": "DAILY-3PM", "strike": "1.1240", "direction": "+", "timestamp": "1563556949.792665"}
